sorpus/__init__.py
sorpus/__version__.py
sorpus/replacer.py
sorpus/sentences.py
sorpus-0.0.1.post2.dist-info/LICENSE
sorpus-0.0.1.post2.dist-info/METADATA
sorpus-0.0.1.post2.dist-info/WHEEL
sorpus-0.0.1.post2.dist-info/top_level.txt
sorpus-0.0.1.post2.dist-info/RECORD
