Metadata-Version: 2.1
Name: sorpus
Version: 0.0.1.post2
Summary: Sentence (Operations) Processing Utilities
Author-email: Siwon Seo <visiopo44@gmail.com>
Project-URL: Homepage, https://github.com/Sion1225/sorpus
Project-URL: Issues, https://github.com/Sion1225/sorpus/issues
Classifier: Programming Language :: Python :: 3
Classifier: License :: OSI Approved :: Apache Software License
Classifier: Operating System :: OS Independent
Requires-Python: >=3.8
License-File: LICENSE
